biomaj_core/__init__.py
biomaj_core/bmajindex.py
biomaj_core/config.py
biomaj_core/mimes-bio.txt
biomaj_core/utils.py
biomaj_core-3.0.28.dist-info/LICENSE
biomaj_core-3.0.28.dist-info/METADATA
biomaj_core-3.0.28.dist-info/WHEEL
biomaj_core-3.0.28.dist-info/top_level.txt
biomaj_core-3.0.28.dist-info/RECORD
