Metadata-Version: 2.1
Name: biomaj-core
Version: 3.0.28
Summary: BioMAJ core library
Home-page: http://biomaj.genouest.org
Author: Olivier Sallou
Author-email: olivier.sallou@irisa.fr
License: UNKNOWN
Download-URL: http://biomaj.genouest.org
Platform: UNKNOWN
Classifier: Development Status :: 5 - Production/Stable
Classifier: Environment :: Console
Classifier: Natural Language :: English
Classifier: Operating System :: POSIX :: Linux
Classifier: Intended Audience :: Science/Research
Classifier: Topic :: Scientific/Engineering :: Bio-Informatics
Classifier: License :: OSI Approved :: GNU Affero General Public License v3 or later (AGPLv3+)
Classifier: Programming Language :: Python :: 3
Requires-Python: >=3
License-File: LICENSE
Requires-Dist: elasticsearch
Requires-Dist: requests
